{
  "country": "Sweden",
  "country_iso": "SE",
  "zentrunk": {
    "inbound": {
      "number_groups": {
        "Sweden Local Voice": "0.003",
        "Sweden Mobile Voice & SMS": "0.003",
        "Sweden National Voice": "0.003",
        "Sweden Tollfree Voice": "0.1262",
        "Sweden local Voice & SMS": "0.003",
        "Sweden mobile Voice": "0.003"
      },
      "rates": {
        "local": [
          "0.003"
        ],
        "mobile": [
          "0.003"
        ],
        "national": [
          "0.003"
        ],
        "tollfree": [
          "0.1262"
        ]
      }
    },
    "local": {
      "inbound": {
        "number_group_rates": {
          "0.003": [
            "Sweden mobile Voice"
          ],
          "0.1262": [
            "Sweden Tollfree Voice"
          ]
        },
        "rate": "0.003",
        "tollfree_rate": "0.1262"
      }
    }
  }
}